pytorch_transfer_learning_debugger/__init__.py
pytorch_transfer_learning_debugger/computational_graph_debugger.py
pytorch_transfer_learning_debugger/torch_debugger.py
pytorch_transfer_learning_debugger/transfer_learning_debugger.py
pytorch_transfer_learning_debugger-0.1.1.dist-info/LICENSE
pytorch_transfer_learning_debugger-0.1.1.dist-info/METADATA
pytorch_transfer_learning_debugger-0.1.1.dist-info/WHEEL
pytorch_transfer_learning_debugger-0.1.1.dist-info/top_level.txt
pytorch_transfer_learning_debugger-0.1.1.dist-info/RECORD
