Metadata-Version: 2.1
Name: pytorch-transfer-learning-debugger
Version: 0.1.1
Summary: A debugger for PyTorch transfer-learning & fine-tuning jobs.
Home-page: https://github.com/yourusername/pytorch-transfer-learning-debugger
Author: Zach Colin Wolpe
Author-email: zachcolinwolpe@gmail.com
Classifier: Development Status :: 3 - Alpha
Classifier: Intended Audience :: Developers
Classifier: Intended Audience :: Science/Research
Classifier: Programming Language :: Python :: 3
Classifier: Programming Language :: Python :: 3.9
Classifier: Topic :: Scientific/Engineering :: Artificial Intelligence
Classifier: License :: OSI Approved :: MIT License
Classifier: Operating System :: OS Independent
Requires-Python: >=3.9
License-File: LICENSE
Requires-Dist: torch>=2.0.0
Requires-Dist: torchvision>=0.15.0
Requires-Dist: numpy>=1.24.0
Requires-Dist: pillow>=9.0.0
Requires-Dist: matplotlib>=3.7.0
Requires-Dist: tqdm>=4.65.0
Provides-Extra: dev
Requires-Dist: pytest>=7.0.0; extra == "dev"
Requires-Dist: black; extra == "dev"
Requires-Dist: flake8; extra == "dev"
Requires-Dist: mypy; extra == "dev"
